Metadata-Version: 2.1
Name: Nobitex
Version: 1.0.0
Summary: python nobitex api
Home-page: https://github.com/aminghani/NobitexAPI
Author: amin ghanizadeh
Author-email: aminkhosroshahi80328@gmail.com
License: MIT
Download-URL: https://github.com/aminghani/NobitexAPI/archive/1.0.0.tar.gz
Keywords: Nobitex,NobitexAPI,pythonNobitex
Platform: UNKNOWN
